MANIFEST.in
README.rst
setup.py
collective/__init__.py
collective.vaporisation.egg-info/PKG-INFO
collective.vaporisation.egg-info/SOURCES.txt
collective.vaporisation.egg-info/dependency_links.txt
collective.vaporisation.egg-info/entry_points.txt
collective.vaporisation.egg-info/namespace_packages.txt
collective.vaporisation.egg-info/not-zip-safe
collective.vaporisation.egg-info/requires.txt
collective.vaporisation.egg-info/top_level.txt
collective/vaporisation/README.txt
collective/vaporisation/__init__.py
collective/vaporisation/adapter.py
collective/vaporisation/config.py
collective/vaporisation/configure.zcml
collective/vaporisation/events.py
collective/vaporisation/i18n.sh
collective/vaporisation/interfaces.py
collective/vaporisation/vocabularies.py
collective/vaporisation/browser/__init__.py
collective/vaporisation/browser/configure.zcml
collective/vaporisation/browser/old_search.pt
collective/vaporisation/browser/old_search.py
collective/vaporisation/browser/search.pt
collective/vaporisation/browser/search.py
collective/vaporisation/locales/collective.vaporisation.pot
collective/vaporisation/locales/it/LC_MESSAGES/collective.vaporisation.mo
collective/vaporisation/locales/it/LC_MESSAGES/collective.vaporisation.po
collective/vaporisation/locales/pt_BR/LC_MESSAGES/collective.vaporisation.mo
collective/vaporisation/locales/pt_BR/LC_MESSAGES/collective.vaporisation.po
collective/vaporisation/portlets/__init__.py
collective/vaporisation/portlets/cloud.pt
collective/vaporisation/portlets/configure.zcml
collective/vaporisation/portlets/customizabletagcloudportlet.py
collective/vaporisation/profiles/default/metadata.xml
collective/vaporisation/profiles/default/portlets.xml
collective/vaporisation/tests/__init__.py
collective/vaporisation/tests/base.py
collective/vaporisation/tests/base_customizabletagcloudportlet.py
collective/vaporisation/tests/test_customizabletagcloudportlet.py
collective/vaporisation/tests/test_doctest.py
docs/HISTORY.txt
docs/INSTALL.txt
docs/LICENSE.GPL
docs/LICENSE.txt